combinator/__init__.py
combinator/environment/__init__.py
combinator/environment/apienv.py
combinator/environment/env.py
combinator/environment/grid.py
combinator/interpreter/__init__.py
combinator/interpreter/globalobjects.py
combinator/interpreter/interpreter.py
combinator/interpreter/makegraph.py
combinator/interpreter/program_expression.py
combinator/interpreter/program_probability.py
combinator/interpreter/type_check.py
combinator-1.2.dist-info/LICENSE
combinator-1.2.dist-info/METADATA
combinator-1.2.dist-info/WHEEL
combinator-1.2.dist-info/top_level.txt
combinator-1.2.dist-info/RECORD
