Metadata-Version: 2.1
Name: combinator
Version: 1.2
Summary: The programming model to integrate AI components
Home-page: https://github.com/swarna-kpaul/combinator
Author: Swarna Kamal Paul
Author-email: swarna.kpaul@gmail.com
Project-URL: Bug Tracker, https://github.com/swarna-kpaul/combinator/issues
Keywords: programming model,dataflow graph,functional programming,API integration,Integrative AI
Classifier: Programming Language :: Python :: 3
Classifier: License :: OSI Approved :: MIT License
Classifier: Operating System :: OS Independent
Requires-Python: >=3.6
License-File: LICENSE
Requires-Dist: sympy (==1.6.2)
Requires-Dist: requests
